tests/attr/test_attr.py
tests/dict/test_filter_dict_nans.py
tests/dict/test_index.py
tests/dict/test_is_subdict.py
tests/dict/test_join_dicts.py
tests/func/test_flatten.py
tests/func/test_is_lambda.py
tests/func/test_mapfunctions.py
tests/list/test_batch_split.py
tests/list/test_has_nulls.py
tests/list/test_prune_list.py
tests/pandas/test_count_duplicates.py
tests/pandas/test_df_to_jsonlist.py
tests/str/test_findall_str.py
tests/str/test_modify_str.py
tests/str/test_partition_n.py
tests/type/test_type_guards.py
urtools/__init__.py
urtools/get_size.py
urtools/attr/__init__.py
urtools/attr/getattrs.py
urtools/attr/getdunder.py
urtools/attr/getpriv.py
urtools/dict/__init__.py
urtools/dict/callback_dict.py
urtools/dict/filter_dict_nans.py
urtools/dict/index.py
urtools/dict/is_subdict.py
urtools/dict/join_dicts.py
urtools/func/__init__.py
urtools/func/flatten.py
urtools/func/is_lambda.py
urtools/func/itertranspose.py
urtools/func/mapfunctions.py
urtools/json/__init__.py
urtools/json/dump_json.py
urtools/json/json_keys2int.py
urtools/json/load_json.py
urtools/list/__init__.py
urtools/list/batch_split.py
urtools/list/has_nulls.py
urtools/list/prune_list.py
urtools/list/split_list.py
urtools/pandas/__init__.py
urtools/pandas/count_duplicates.py
urtools/pandas/df_to_jsonlist.py
urtools/pandas/find_duplicates.py
urtools/str/__init__.py
urtools/str/findall_str.py
urtools/str/modify_str.py
urtools/str/partition_n.py
urtools/type/__init__.py
urtools/type/type_guards.py
urtools-0.0.4.dist-info/LICENSE
urtools-0.0.4.dist-info/METADATA
urtools-0.0.4.dist-info/WHEEL
urtools-0.0.4.dist-info/top_level.txt
urtools-0.0.4.dist-info/RECORD
