Metadata-Version: 2.1
Name: urtools
Version: 0.0.4
Summary: Custom functions and other utilities that I find useful and use across many projects.
Author-email: MatthewBaggins <bagginsmatthew@gmail.com>
License: MIT License
Project-URL: Homepage, https://github.com/MatthewBaggins/urtools
Keywords: utils
Classifier: License :: OSI Approved :: MIT License
Classifier: Programming Language :: Python
Classifier: Programming Language :: Python :: 3
Classifier: Operating System :: OS Independent
Requires-Python: >=3.8
License-File: LICENSE
Requires-Dist: numpy
Requires-Dist: pandas (>=1.5.3)
Requires-Dist: typing-extensions
Provides-Extra: dev
Requires-Dist: black ; extra == 'dev'
Requires-Dist: pylint ; extra == 'dev'
Requires-Dist: pip-tools ; extra == 'dev'
Requires-Dist: pytest ; extra == 'dev'
